brvmpy/__init__.py
brvmpy/actions.py
brvmpy/indices.py
brvmpy/obligations.py
brvmpy/scraper.py
brvmpy/utils.py
brvmpy/volumes.py
brvmpy-0.1.0.dist-info/licenses/LICENSE
brvmpy-0.1.0.dist-info/METADATA
brvmpy-0.1.0.dist-info/WHEEL
brvmpy-0.1.0.dist-info/top_level.txt
brvmpy-0.1.0.dist-info/RECORD
