Metadata-Version: 2.4
Name: brvmpy
Version: 0.1.0
Summary: Scrape financial data from BRVM (Bourse Régionale des Valeurs Mobilières)
Home-page: https://github.com/idrissbado/BRVMpy
Author: Idriss Badolivier
Author-email: Idriss Badolivier <idrissbadoolivier@gmail.com>
Project-URL: Homepage, https://github.com/idrissbado/BRVMpy
Project-URL: Bug Reports, https://github.com/idrissbado/BRVMpy/issues
Project-URL: Source, https://github.com/idrissbado/BRVMpy
Classifier: Development Status :: 4 - Beta
Classifier: Intended Audience :: Developers
Classifier: Intended Audience :: Financial and Insurance Industry
Classifier: Topic :: Office/Business :: Financial :: Investment
Classifier: License :: OSI Approved :: MIT License
Classifier: Programming Language :: Python :: 3
Classifier: Programming Language :: Python :: 3.8
Classifier: Programming Language :: Python :: 3.9
Classifier: Programming Language :: Python :: 3.10
Classifier: Programming Language :: Python :: 3.11
Classifier: Programming Language :: Python :: 3.12
Requires-Python: >=3.8
License-File: LICENSE
Requires-Dist: selenium>=4.15.0
Requires-Dist: pandas>=2.0.0
Requires-Dist: webdriver-manager>=4.0.0
Dynamic: author
Dynamic: home-page
Dynamic: license-file
Dynamic: requires-python
